{"files":{"basic curry":"basic-curry","basic sponge cake":"basic-sponge-cake","brandy butter":"brandy-butter","bread":"bread","celeriac waffles":"celeriac-waffles","microwave mug cake":"chocolate-mug-cake","christmas pudding":"christmas-pudding","custard":"custard","mother's pancakes":"mothers-pancakes","popovers":"popovers","savory cake":"savory-cake","steak and kidney pie":"steak-and-kidney-pie","tasty fish":"tasty-fish","vegan chocolate cake":"vegan-chocolate-cake"},"words":{"basic":[0,1],"chili":[0],"curry":[0],"diced":[0],"garlic":[0,4,12],"onion":[0,4],"butter":[1,2,3,5,8],"cake":[1,5,10,13],"eggs":[1,4,9,10],"flour":[1,3,5,6,8,9,10,11,13],"sponge":[1],"sugar":[1,2,3,5,6,7,8,13],"boiling":[2],"brandy":[2],"coconut":[2],"icing":[2,13],"oil":[2,5,6,10,11,13],"water":[2,3],"bread":[3,6],"dash":[3],"egg":[3,5,7,8],"salt":[3,4,8,9,10],"vinegar":[3],"yeast":[3],"black":[4,10],"celeriac":[4],"granules":[4],"grated":[4],"ground":[4],"pepper":[4,10],"tsp":[4,7,8,9,10],"waffles":[4],"chips":[5],"chocolate":[5,13],"cocoa":[5,13],"coffee":[5],"microwave":[5],"milk":[5,7,8,9,10,13],"mug":[5],"not":[5],"optional":[5],"peanut":[5],"self-rising":[5],"small":[5],"splash":[5],"tbsp":[5],"teaspoon":[5],"vanilla":[5,7,13],"christmas":[6],"fruit":[6],"lemon":[6,12],"mixed":[6],"orange":[6],"pudding":[6],"rindjuice":[6],"spices":[6],"cornflour":[7],"cream":[7],"custard":[7],"extract":[7,13],"single":[7],"yolks":[7],"baking":[8],"caster":[8],"melted":[8],"mothers":[8],"natural":[8],"pancakes":[8],"plain":[8],"powder":[8],"yoghurt":[8,10],"cup":[9],"popovers":[9],"cheese":[10],"chopped":[10],"cubed":[10],"freshly-ground":[10],"goats":[10],"olive":[10],"pinch":[10],"pistachios":[10],"prunes":[10],"raising":[10],"roughly":[10],"savory":[10],"soft":[10],"and":[11],"beef":[11],"carrots":[11],"kidney":[11],"mashing":[11],"onions":[11],"pie":[11],"steak":[11],"stock":[11],"veg":[11],"fish":[12],"juice":[12],"new":[12],"potatoes":[12],"prosciutto":[12],"rainbow":[12],"samfire":[12],"tasty":[12],"trout":[12],"almond":[13],"avocado":[13],"soya":[13],"sunflower":[13],"unsweetened":[13],"vegan":[13],"vegetable":[13]}}
